LICENSE.txt
MANIFEST.in
README.md
setup.cfg
setup.py
pyTrivialCache/__init__.py
pyTrivialCache/__main__.py
pyTrivialCache/pyTrivialCache.py
pyTrivialCache.egg-info/PKG-INFO
pyTrivialCache.egg-info/SOURCES.txt
pyTrivialCache.egg-info/dependency_links.txt
pyTrivialCache.egg-info/entry_points.txt
pyTrivialCache.egg-info/top_level.txt