Metadata-Version: 1.0
Name: pyTrivialCache
Version: 0.3.0
Summary: The poor man's API for manipulating a file system cache.
Home-page: https://github.com/robertoreale/pyTrivialCache
Author: Roberto Reale
Author-email: rober.reale@gmail.com
License: UNKNOWN
Keywords: filesystem,cache
Platform: UNKNOWN
